pygeogrids/__init__.py
pygeogrids/geodetic_datum.py
pygeogrids/grids.py
pygeogrids/nearest_neighbor.py
pygeogrids/netcdf.py
pygeogrids/plotting.py
pygeogrids/shapefile.py
pygeogrids/shapefiles/ne_110m_admin_0_countries.dbf
pygeogrids/shapefiles/ne_110m_admin_0_countries.prj
pygeogrids/shapefiles/ne_110m_admin_0_countries.qpj
pygeogrids/shapefiles/ne_110m_admin_0_countries.shp
pygeogrids/shapefiles/ne_110m_admin_0_countries.shx
pygeogrids-0.5.3.dist-info/licenses/AUTHORS.rst
pygeogrids-0.5.3.dist-info/licenses/LICENSE.txt
pygeogrids-0.5.3.dist-info/METADATA
pygeogrids-0.5.3.dist-info/WHEEL
pygeogrids-0.5.3.dist-info/top_level.txt
pygeogrids-0.5.3.dist-info/RECORD
