Metadata-Version: 2.4
Name: pygeogrids
Version: 0.5.3
Summary: Module for creation and handling of discrete global grids
Home-page: https://github.com/TUW-GEO/pygeogrids/
Author: TU Wien
Author-email: remote.sensing@geo.tuwien.ac.at
License: mit
Project-URL: Documentation, http://pygeogrids.readthedocs.org/
Platform: any
Classifier: Development Status :: 4 - Beta
Classifier: Programming Language :: Python
Requires-Python: >=3.8
License-File: LICENSE.txt
License-File: AUTHORS.rst
Requires-Dist: importlib-metadata; python_version < "3.8"
Requires-Dist: numpy
Requires-Dist: pandas
Requires-Dist: netCDF4
Requires-Dist: pyproj
Requires-Dist: pykdtree
Requires-Dist: scipy
Provides-Extra: testing
Requires-Dist: pytest; extra == "testing"
Requires-Dist: pytest-cov; extra == "testing"
Provides-Extra: docs
Requires-Dist: ipykernel; extra == "docs"
Requires-Dist: nbconvert; extra == "docs"
Requires-Dist: matplotlib; extra == "docs"
Requires-Dist: nbsphinx; extra == "docs"
Requires-Dist: sphinx_rtd_theme; extra == "docs"
Dynamic: license-file
